graph_express/__init__.py
graph_express/__main__.py
graph_express/__version__.py
graph_express/cli.py
graph_express/graph_express.py
graph_express/utils.py
graph_express/base/__init__.py
graph_express/base/centrality.py
graph_express/base/community.py
graph_express/base/convert.py
graph_express/base/draw.py
graph_express/base/graph.py
graph_express/base/layout.py
graph_express/base/subgraph.py
graph_express-1.0a3.dist-info/LICENSE.md
graph_express-1.0a3.dist-info/METADATA
graph_express-1.0a3.dist-info/WHEEL
graph_express-1.0a3.dist-info/entry_points.txt
graph_express-1.0a3.dist-info/top_level.txt
graph_express-1.0a3.dist-info/RECORD
