Metadata-Version: 2.1
Name: graph_express
Version: 1.0a3
Summary: Python package for the analysis and visualization of network graphs.
Home-page: https://github.com/nelsonaloysio/graph-express
Author: ['Nelson Aloysio Reis de Almeida Passos']
License: MIT
Project-URL: Source, https://github.com/nelsonaloysio/graph_express
Project-URL: Tracker, https://github.com/nelsonaloysio/graph_express/issues
Keywords: network graph
Classifier: Development Status :: 3 - Alpha
Classifier: Intended Audience :: Developers
Classifier: Intended Audience :: Information Technology
Classifier: Intended Audience :: Science/Research
Classifier: License :: OSI Approved :: MIT License
Classifier: Programming Language :: Python :: 3
Classifier: Topic :: Scientific/Engineering :: Information Analysis
Classifier: Topic :: Scientific/Engineering :: Visualization
Classifier: Topic :: Software Development :: Libraries :: Python Modules
Requires-Python: >=3.6
License-File: LICENSE.md
Requires-Dist: cdlib >=0.3.0
Requires-Dist: datashader >=0.10.0
Requires-Dist: kaleido >=0.2.1
Requires-Dist: leidenalg >=0.8.3
Requires-Dist: networkit >=7.0
Requires-Dist: networkx >=2.3
Requires-Dist: networkx-gdf >=1.1
Requires-Dist: openpyxl >=3.1.2
Requires-Dist: pandas >=0.25.3
Requires-Dist: plotly >=3.10.0
Requires-Dist: python-igraph >=0.8.3
Requires-Dist: python-louvain >=0.14
